embedl/__init__.py
embedl/models/__init__.py
embedl/models/flash_head.py
embedl/models/gemma/__init__.py
embedl/models/gemma/modeling_flash_head.py
embedl/models/llama/__init__.py
embedl/models/llama/modeling_flash_head.py
embedl/models/qwen/__init__.py
embedl/models/qwen/modeling_flash_head.py
embedl/models/vllm/__init__.py
embedl/models/vllm/demo.py
embedl/models/vllm/patching/logits_processor.py
embedl/models/vllm/patching/sampler.py
embedl_models-2025.12.1.dist-info/licenses/LICENSE
embedl_models-2025.12.1.dist-info/METADATA
embedl_models-2025.12.1.dist-info/WHEEL
embedl_models-2025.12.1.dist-info/top_level.txt
embedl_models-2025.12.1.dist-info/RECORD
