Metadata-Version: 2.4
Name: embedl_models
Version: 2025.12.1
Summary: Efficient deep learning models for the edge.
Requires-Python: >=3.10
License-File: LICENSE
Requires-Dist: vllm<=0.13.0,>=0.11.0
Requires-Dist: accelerate==1.12.0
Dynamic: license-file
